MANIFEST.in
README.rst
setup.cfg
setup.py
scipio/VERSION
scipio/__init__.py
scipio/build.py
scipio/command_line.py
scipio/download.py
scipio/main.py
scipio.egg-info/PKG-INFO
scipio.egg-info/SOURCES.txt
scipio.egg-info/dependency_links.txt
scipio.egg-info/entry_points.txt
scipio.egg-info/requires.txt
scipio.egg-info/top_level.txt
tests/__init__.py
tests/test_build.py
tests/test_download.py
tests/test_main.py