Metadata-Version: 1.1
Name: scipio
Version: 0.4.2
Summary: Automate github downloads and xcodebuild
Home-page: https://github.com/mikekreuzer/scipio
Author: Mike Kreuzer
Author-email: motherfunctor@yahoo.com.au
License: MIT
Keywords: xcode xcodebuild github Carthage Cocoapods
Platform: osx
Classifier: Development Status :: 3 - Alpha
Classifier: Environment :: MacOS X
Classifier: Intended Audience :: Developers
Classifier: Topic :: Software Development :: Build Tools
Classifier: License :: OSI Approved :: MIT License
Classifier: Programming Language :: Python :: 2
Classifier: Programming Language :: Python :: 3
